regius/__init__.py
regius-0.0.4.dist-info/LICENSE
regius-0.0.4.dist-info/METADATA
regius-0.0.4.dist-info/WHEEL
regius-0.0.4.dist-info/top_level.txt
regius-0.0.4.dist-info/RECORD
