Metadata-Version: 2.1
Name: regius
Version: 0.0.4
Summary: regius - Python Handsome Web Framework
Home-page: https://github.com/alalawy/regius
Author: M Nasrul Alawy
Author-email: alawy.nasrul@gmail.com
License: UNKNOWN
Platform: UNKNOWN
Classifier: Programming Language :: Python :: 3
Classifier: License :: OSI Approved :: MIT License
Classifier: Operating System :: OS Independent
Requires-Python: >=3.6
Requires-Dist: webob
Requires-Dist: parse
Requires-Dist: jinja2
Requires-Dist: whitenoise
Requires-Dist: gunicorn
Requires-Dist: sqlalchemy
Requires-Dist: pymysql
